manim_tikz/__init__.py
manim_tikz/template.py
manim_tikz/tikz.py
manim_tikz-0.0.1a1.dist-info/entry_points.txt
manim_tikz-0.0.1a1.dist-info/WHEEL
manim_tikz-0.0.1a1.dist-info/METADATA
manim_tikz-0.0.1a1.dist-info/RECORD
