Metadata-Version: 2.1
Name: manim-tikz
Version: 0.0.1a1
Summary: Converts Tikz markup code into an SVGMobject for use in manim.
Home-page: https://github.com/ralphieraccoon/manim-tikz
Author: Ralphie Raccoon
Author-email: damian.crosby@manchester.ac.uk
Requires-Python: >=3.8,<3.12
Classifier: Programming Language :: Python :: 3
Classifier: Programming Language :: Python :: 3.8
Classifier: Programming Language :: Python :: 3.9
Classifier: Programming Language :: Python :: 3.10
Classifier: Programming Language :: Python :: 3.11
Requires-Dist: manim (>=0.17.0)
Project-URL: Bug Tracker, https://github.com/ralphieraccoon/manim-tikz/issues
Project-URL: Repository, https://github.com/ralphieraccoon/manim-tikz
